ossp_sdk/__init__.py
ossp_sdk/client.py
ossp_sdk-0.1.0.dist-info/licenses/LICENSE
ossp_sdk-0.1.0.dist-info/METADATA
ossp_sdk-0.1.0.dist-info/WHEEL
ossp_sdk-0.1.0.dist-info/top_level.txt
ossp_sdk-0.1.0.dist-info/RECORD
