Metadata-Version: 2.4
Name: ossp-sdk
Version: 0.1.0
Summary: CloudEvents-first Python SDK for the Open Safety Signal Protocol (OSSP).
Author-email: OSSP Working Group <info@ossp.io>
License:                                  Apache License
Project-URL: Homepage, https://ossp.io
Project-URL: Documentation, https://ossp.io/sdk.html
Project-URL: Specification, https://ossp.io/specification.html
Project-URL: Repository, https://github.com/Open-Safety-Signal-Protocol/sdk-python
Project-URL: Issues, https://github.com/Open-Safety-Signal-Protocol/sdk-python/issues
Project-URL: Changelog, https://github.com/Open-Safety-Signal-Protocol/sdk-python/releases
Classifier: Programming Language :: Python :: 3
Classifier: Operating System :: OS Independent
Classifier: Intended Audience :: Developers
Classifier: Topic :: System :: Monitoring
Requires-Python: >=3.8
License-File: LICENSE
Requires-Dist: requests>=2.25.0
Provides-Extra: validate
Requires-Dist: jsonschema>=4.18; extra == "validate"
Dynamic: license-file
